daikinapi/__init__.py
daikinapi/daikinapi.py
daikinapi/example.py
daikinapi/setup.py
daikinapi-1.0.8.dist-info/LICENSE
daikinapi-1.0.8.dist-info/METADATA
daikinapi-1.0.8.dist-info/WHEEL
daikinapi-1.0.8.dist-info/top_level.txt
daikinapi-1.0.8.dist-info/RECORD
