Metadata-Version: 2.1
Name: daikinapi
Version: 1.0.8
Summary: Get metrics from Daikin airconditioning unit wifi module
Home-page: https://github.com/arska/python-daikinapi
Author: Aarno Aukia
Author-email: aarno@aukia.com
License: MIT
Keywords: Daikin,airconditioning,API
Classifier: Intended Audience :: Developers
Classifier: License :: OSI Approved :: MIT License
Classifier: Programming Language :: Python :: 3.6
Classifier: Programming Language :: Python :: 3.7
Classifier: Programming Language :: Python :: 3.8
Classifier: Programming Language :: Python :: 3.9
Requires-Python: >=3.6
License-File: LICENSE
Requires-Dist: requests (>=2)
Requires-Dist: urllib3 (>=1.24)
Provides-Extra: dev
Requires-Dist: tox ; extra == 'dev'
